mon_test/__init__.py
mon_test/mon_test_script.py
mon_premier_packageNT0102-0.0.1.dist-info/LICENCE
mon_premier_packageNT0102-0.0.1.dist-info/METADATA
mon_premier_packageNT0102-0.0.1.dist-info/WHEEL
mon_premier_packageNT0102-0.0.1.dist-info/top_level.txt
mon_premier_packageNT0102-0.0.1.dist-info/RECORD
